mgr_ovh/__init__.py
mgr_ovh/dns.py
mgr_ovh-0.0.2.dist-info/LICENSE
mgr_ovh-0.0.2.dist-info/METADATA
mgr_ovh-0.0.2.dist-info/WHEEL
mgr_ovh-0.0.2.dist-info/top_level.txt
mgr_ovh-0.0.2.dist-info/RECORD
